w2t_bkin/__init__.py
w2t_bkin/config.py
w2t_bkin/exceptions.py
w2t_bkin/metadata.py
w2t_bkin/models.py
w2t_bkin/ttl.py
w2t_bkin/utils.py
w2t_bkin/cli/__init__.py
w2t_bkin/cli/__main__.py
w2t_bkin/cli/data.py
w2t_bkin/cli/env.py
w2t_bkin/cli/pipeline.py
w2t_bkin/cli/server.py
w2t_bkin/cli/utils.py
w2t_bkin/cli/validation.py
w2t_bkin/cli/worker.py
w2t_bkin/core/__init__.py
w2t_bkin/core/session.py
w2t_bkin/core/validate.py
w2t_bkin/data/__init__.py
w2t_bkin/data/manager.py
w2t_bkin/figures/__init__.py
w2t_bkin/figures/ecephys.py
w2t_bkin/figures/pose.py
w2t_bkin/figures/profiling.py
w2t_bkin/figures/sync.py
w2t_bkin/flows/__init__.py
w2t_bkin/flows/batch.py
w2t_bkin/flows/session.py
w2t_bkin/ingest/__init__.py
w2t_bkin/ingest/behavior.py
w2t_bkin/ingest/bpod.py
w2t_bkin/ingest/events.py
w2t_bkin/ingest/kilosort.py
w2t_bkin/ingest/pose.py
w2t_bkin/ingest/spikeglx.py
w2t_bkin/operations/__init__.py
w2t_bkin/operations/assembly.py
w2t_bkin/operations/discovery.py
w2t_bkin/operations/finalization.py
w2t_bkin/operations/ingestion.py
w2t_bkin/operations/pose_generator.py
w2t_bkin/operations/sync.py
w2t_bkin/operations/verification.py
w2t_bkin/processors/__init__.py
w2t_bkin/processors/dlc.py
w2t_bkin/processors/facemap.py
w2t_bkin/processors/transcode.py
w2t_bkin/sync/__init__.py
w2t_bkin/sync/core.py
w2t_bkin/sync/stats.py
w2t_bkin/sync/timebase.py
w2t_bkin/sync/ttl.py
w2t_bkin/sync/ttl_mock.py
w2t_bkin/sync/ttl_robust.py
w2t_bkin/tasks/__init__.py
w2t_bkin/tasks/artifacts.py
w2t_bkin/tasks/assembly.py
w2t_bkin/tasks/discovery.py
w2t_bkin/tasks/finalization.py
w2t_bkin/tasks/ingestion.py
w2t_bkin/tasks/initialization.py
w2t_bkin/tasks/sync.py
w2t_bkin/templates/.env.template
w2t_bkin/templates/.workers-README.md
w2t_bkin/templates/configuration.toml.template
w2t_bkin/templates/full-metadata.toml.template
w2t_bkin/tools/__init__.py
w2t_bkin/tools/mat2json.py
w2t_bkin/tools/pose2ttl.py
w2t_bkin/tools/trials2df.py
w2t_bkin-0.0.14.dist-info/entry_points.txt
w2t_bkin-0.0.14.dist-info/licenses/LICENSE
w2t_bkin-0.0.14.dist-info/WHEEL
w2t_bkin-0.0.14.dist-info/METADATA
w2t_bkin-0.0.14.dist-info/RECORD
