Metadata-Version: 2.4
Name: w2t-bkin
Version: 0.0.14
Summary: Mouse wiskers body kinematics and behavior
Author: Larkum Lab
Requires-Python: ~=3.10.0
Classifier: Programming Language :: Python :: 3
Classifier: License :: OSI Approved :: Apache Software License
Classifier: Intended Audience :: Science/Research
Classifier: Topic :: Scientific/Engineering :: Information Analysis
License-File: LICENSE
Requires-Dist: pydantic~=2.12.0
Requires-Dist: pydantic-settings~=2.11.0
Requires-Dist: tomli~=2.3.0
Requires-Dist: tomli_w~=1.2.0
Requires-Dist: typer~=0.19.0
Requires-Dist: rich~=14.2.0
Requires-Dist: pynwb~=3.1.0
Requires-Dist: hdmf~=4.1.0
Requires-Dist: prefect~=3.6.0
Requires-Dist: prefect-docker~=0.7.0
Requires-Dist: asyncpg~=0.29.0
Requires-Dist: scipy~=1.15.0
Requires-Dist: numpy~=1.26.4
Requires-Dist: black~=25.9.0 ; extra == "dev"
Requires-Dist: isort~=7.0.0 ; extra == "dev"
Requires-Dist: pytest~=9.0.0 ; extra == "dev"
Requires-Dist: pytest-cov~=6.0.0 ; extra == "dev"
Requires-Dist: matplotlib~=3.8.0 ; extra == "dev"
Requires-Dist: numpy~=1.26.0 ; extra == "dev"
Requires-Dist: nwbinspector~=0.6.5 ; extra == "worker"
Requires-Dist: ndx-structured-behavior ; extra == "worker"
Requires-Dist: ndx-pose ; extra == "worker"
Requires-Dist: ndx-events ; extra == "worker"
Requires-Dist: ffmpeg-python~=0.2.0 ; extra == "worker"
Requires-Dist: pandas~=2.3.0 ; extra == "worker"
Requires-Dist: h5py~=3.15.0 ; extra == "worker"
Requires-Dist: tables~=3.10.0 ; extra == "worker"
Requires-Dist: matplotlib~=3.8.0 ; extra == "worker"
Provides-Extra: dev
Provides-Extra: worker
